[
  {
    "Id": "GN-2024-03-29-1234",
    "UserName": "EmilySmith87",
    "Email": "emilysmith@gmail.com",
    "PhoneNumber": "12345678901",
    "FirstName": "Emily",
    "LastName": "Smith",
    "Address": {
      "Street": "123 Oak Street",
      "Region": "Eastside",
      "City": "Springfield",
      "Country": "United States"
    },
    "Gender": "M",
    "BOD": "1997-07-28",
    "HardwareId": "F2AA9B1CDD5E"
  },
  {
    "Id": "GD-2024-03-29-5678",
    "UserName": "JohnDoe_24",
    "Email": "johndoe@gmail.com",
    "PhoneNumber": "23456789012",
    "FirstName": "John",
    "LastName": "Doe",
    "Address": {
      "Street": "456 Maple Avenue",
      "Region": "Downtown",
      "City": "Rivertown",
      "Country": "Canada"

    },
    "Gender": "F",
    "BOD": "1980-10-01",
    "HardwareId": "3C4E782BAFF0"
  },
  {
    "Id": "GT-2024-03-29-91011",
    "UserName": "SarahJohnson123",
    "Email": "sarahjohnson@gmail.com",
    "PhoneNumber": "34567890123",
    "FirstName": "Sarah",
    "LastName": "Johnson",
    "Address": {
      "Street": "789 Pine Road",
      "Region": "West End",
      "City": "Meadowville",
      "Country": "Australia"
    },
    "Gender": "F",
    "BOD": "1977-09-03",
    "HardwareId": "A15BDF3987DE"
  },
  {
    "Id": "GQ-2024-03-29-121314",
    "UserName": "AlexBrown8282",
    "Email": "alexbrown82@gmail.com",
    "PhoneNumber": "45678901234",
    "FirstName": "Alex",
    "LastName": "Brown",
    "Address": {
      "Street": "321 Elm Street",
      "Region": "Northside",
      "City": "Hilltown",
      "Country": "United Kingdom"
    },
    "Gender": "M",
    "BOD": "1966-07-28",
    "HardwareId": "162D0F51CBE9"
  },
  {
    "Id": "GM-2024-03-29-151617",
    "UserName": "Jessica_Walker",
    "Email": "jessicawalker@gmail.com",
    "PhoneNumber": "56789012345",
    "FirstName": "Jessica",
    "LastName": "Walker",
    "Address": {
      "Street": "567 Birch Lane",
      "Region": "Southside",
      "City": "Garden City",
      "Country": "New Zealand"
    },
    "Gender": "F",
    "BOD": "1998-12-28",
    "HardwareId": "7E9FA1CD0321"
  },
  {
    "Id": "GM-2024-03-29-084512",
    "UserName": "ZenithFlare",
    "Email": "zenithflare@gmail.com",
    "PhoneNumber": "67890123456",
    "FirstName": "zenith",
    "LastName": "Flare",
    "Address": {
      "Street": "890 Oak Street",
      "Region": "Northview",
      "City": "Garden City",
      "Country": "New Zealand"
    },
    "Gender": "M",
    "BOD": "1998-06-20",
    "HardwareId": "EB02C34FE153"
  },
  {
    "Id": "GM-2024-03-29-235959",
    "UserName": "LunaSilver",
    "Email": "lunasilver@gmail.com",
    "PhoneNumber": "78901234567",
    "FirstName": "Luna",
    "LastName": "Silver",
    "Address": {
      "Street": "456 Pine Street",
      "Region": "Westside",
      "City": "Garden City",
      "Country": "New Zealand"
    },
    "Gender": "F",
    "BOD": "1977-12-28",
    "HardwareId": "5D14E5622975"
  },
  {
    "Id": "GM-2024-03-29-123456",
    "UserName": "SparklingDreams23",
    "Email": "sparklingdreams@gmail.com",
    "PhoneNumber": "89012345678",
    "FirstName": "Sparkling",
    "LastName": "dreams",
    "Address": {
      "Street": "789 Oak Avenue",
      "Region": "North Hills",
      "City": "Riverdale",
      "Country": "New Zealand"
    },
    "Gender": "F",
    "BOD": "2002-09-28",
    "HardwareId": "CF2607746197"
  },
  {
    "Id": "GM-2024-03-29-789012",
    "UserName": "MountainExplorer42",
    "Email": "mountainexplorer@gmail.com",
    "PhoneNumber": "98765432109",
    "FirstName": "mountain",
    "LastName": "explorer",
    "Address": {
      "Street": "789 Oak Avenue",
      "Region": "North Hills",
      "City": "Riverdale",
      "Country": "New Zealand"
    },
    "Gender": "F",
    "BOD": "2004-05-28",
    "HardwareId": "40382986A3BE"
  },
  {
    "Id": "GM-2024-03-29-345678",
    "UserName": "TechGuru89",
    "Email": "techguru@gmail.com",
    "PhoneNumber": "87654321098",
    "FirstName": "tech",
    "LastName": "guru",
    "Address": {
      "Street": "123 Elm Street",
      "Region": "Southside",
      "City": "Hilltop",
      "Country": "New Zealand"
    },
    "Gender": "F",
    "BOD": "2007-04-28",
    "HardwareId": "B14A4B98E5DF"
  }
]